mobject.py
setup.py
mobject.egg-info/PKG-INFO
mobject.egg-info/SOURCES.txt
mobject.egg-info/dependency_links.txt
mobject.egg-info/not-zip-safe
mobject.egg-info/top_level.txt