Metadata-Version: 1.0
Name: mobject
Version: 0.1.1
Summary: Lightweight library to construct objects and object trees
Home-page: http://github.com/tobgu/mobject
Author: Tobias Gustafsson
Author-email: tobias.l.gustafsson@gmail.com
License: LICENCE.mit
Platform: UNKNOWN
